setup.py
ase/__init__.py
pyase.egg-info/PKG-INFO
pyase.egg-info/SOURCES.txt
pyase.egg-info/dependency_links.txt
pyase.egg-info/top_level.txt