Metadata-Version: 1.0
Name: pyase
Version: 0.0.6
Summary: Bindings for .ASE and .ASEXE (not yet) files.
Home-page: UNKNOWN
Author: UNKNOWN
Author-email: UNKNOWN
License: UNKNOWN
Platform: UNKNOWN
